{
    "products": [
        {
            "title": "title1",
            "id": 1,
            "price": 2.24,
            "imageSrc": "imgScr"
        },
        {
            "title": "title2",
            "id": 2,
            "price": 0.24,
            "imageSrc": "imgScr"
        },
        {
            "title": "title3",
            "id": 3,
            "price": 1.24123,
            "imageSrc": "imgScr"
        },
        {
            "title": "title4",
            "id": 4,
            "price": 0.24,
            "imageSrc": "imgScr"
        },
        {
            "title": "title5",
            "id": 5,
            "price": 204.24,
            "imageSrc": "imgScr"
        },
        {
            "title": "title6",
            "id": 6,
            "price": 8.24,
            "imageSrc": "imgScr"
        },
        {
            "title": "title7",
            "id": 7,
            "price": 12.24,
            "imageSrc": "imgScr"
        },
        {
            "title": "title8",
            "id": 8,
            "price": 1.240,
            "imageSrc": "imgScr"
        },
        {
            "title": "title9",
            "id": 9,
            "price": 0.94,
            "imageSrc": "imgScr"
        },
        {
            "title": "title10",
            "id": 10,
            "price": 1.24,
            "imageSrc": "imgScr"
        },
        {
            "title": "title11",
            "id": 11,
            "price": 1.24,
            "imageSrc": "imgScr"
        },
        {
            "title": "title12",
            "id": 12,
            "price": 1.24,
            "imageSrc": "imgScr"
        },
        {
            "title": "title13",
            "id": 13,
            "price": 1.24,
            "imageSrc": "imgScr"
        },
        {
            "title": "title14",
            "id": 14,
            "price": 1.24,
            "imageSrc": "imgScr"
        },
        {
            "title": "title15",
            "id": 15,
            "price": 1.24,
            "imageSrc": "imgScr"
        }
    ]
}